README.md
mcp_claude_command/__init__.py
mcp_claude_command-0.6.0.dist-info/METADATA
mcp_claude_command-0.6.0.dist-info/WHEEL
mcp_claude_command-0.6.0.dist-info/entry_points.txt
mcp_claude_command-0.6.0.dist-info/RECORD
