Metadata-Version: 2.4
Name: mcp-claude-command
Version: 0.6.0
Summary: Namespace alias for claude-command - AI command center for Claude Code
Project-URL: Homepage, https://github.com/shaneholloman/mcp-claude-command
Project-URL: Repository, https://github.com/shaneholloman/mcp-claude-command
Project-URL: Issues, https://github.com/shaneholloman/mcp-claude-command/issues
Author-email: Shane Holloman <shane@shaneholloman.com>
License: MIT
Keywords: ai,assistant,claude,command,mcp
Classifier: Development Status :: 4 - Beta
Classifier: Intended Audience :: Developers
Classifier: License :: OSI Approved :: MIT License
Classifier: Programming Language :: Python :: 3
Classifier: Programming Language :: Python :: 3.11
Classifier: Programming Language :: Python :: 3.12
Classifier: Programming Language :: Python :: 3.13
Requires-Python: >=3.11
Requires-Dist: claude-command==0.6.0
